mathseq/__init__.py
mathseq/funcs.py
mathseq/seq.py
mathseq-0.0.3.dist-info/LICENSE
mathseq-0.0.3.dist-info/METADATA
mathseq-0.0.3.dist-info/WHEEL
mathseq-0.0.3.dist-info/top_level.txt
mathseq-0.0.3.dist-info/RECORD
