Metadata-Version: 2.1
Name: mathseq
Version: 0.0.3
Summary: A Python library that generates integer sequences
Home-page: https://github.com/TheGreatestShoaib/Mathseq
Author: Shoaib Islam
Author-email: shoaibislam.sh@gmail.com
License: UNKNOWN
Project-URL: Bug Reports, https://github.com/TheGreatestShoaib/MathSeq/issues
Project-URL: Source, https://github.com/TheGreatestShoaib/MathSeq/
Keywords: sequence,generator,fibonacci
Platform: UNKNOWN
Classifier: Development Status :: 3 - Alpha
Classifier: Intended Audience :: Developers
Classifier: Topic :: Software Development :: Build Tools
Classifier: License :: OSI Approved :: MIT License
Classifier: Programming Language :: Python :: 3
Classifier: Programming Language :: Python :: 3.3
Classifier: Programming Language :: Python :: 3.4
Classifier: Programming Language :: Python :: 3.5
Classifier: Programming Language :: Python :: 3.6
Classifier: Programming Language :: Python :: 3.7
Classifier: Programming Language :: Python :: 3.8
Classifier: Programming Language :: Python :: 3.9
Classifier: Programming Language :: Python :: 3 :: Only
Requires-Python: >=3.3, <4
License-File: LICENSE
